nexri/__init__.py
nexri/dense.py
nexri/tests/__init__.py
nexri/tests/test_dense.py
nexri-0.1.0.dist-info/licenses/LICENSE
nexri-0.1.0.dist-info/METADATA
nexri-0.1.0.dist-info/WHEEL
nexri-0.1.0.dist-info/top_level.txt
nexri-0.1.0.dist-info/RECORD
