Metadata-Version: 2.4
Name: nexri
Version: 0.1.0
Summary: Advanced layers for TensorFlow Keras
Home-page: https://github.com/nexri/nexri
Author: Pawel Tomkiewicz
Author-email: Pawel Tomkiewicz <pawel.tomkiewicz@nexri.eu>
License: MIT
Project-URL: Homepage, https://github.com/nexri/nexri
Project-URL: Bug Tracker, https://github.com/nexri/nexri/issues
Project-URL: Documentation, https://github.com/nexri/nexri#readme
Keywords: keras,tensorflow,deep-learning,neural-network,machine-learning
Classifier: Programming Language :: Python :: 3
Classifier: License :: OSI Approved :: MIT License
Classifier: Operating System :: OS Independent
Classifier: Topic :: Scientific/Engineering :: Artificial Intelligence
Requires-Python: >=3.9
License-File: LICENSE
Requires-Dist: tensorflow>=2.19.0
Dynamic: author
Dynamic: home-page
Dynamic: license-file
Dynamic: requires-python
